bisectex
